{
  "id": null,
  "user_id": null,
  "original_text": "OFERTA LABORAL\nTECHNOVATE SOLUTIONS S.A.S.\nCargo: Desarrollador Full Stack Senior\nUbicación: Bogotá, Colombia (Modalidad híbrida)\nTipo de contrato: Término indefinido\nFecha de publicación: 4 de diciembre de 2025\nSOBRE NOSOTROS\nTechNovate Solutions es una empresa líder en desarrollo de soluciones tecnológicas para\nel sector financiero y retail en América Latina. Contamos con más de 10 años de\nexperiencia y un equipo de más de 200 profesionales trabajando en proyectos\ninnovadores.\nDESCRIPCIÓN DEL CARGO\nBuscamos un Desarrollador Full Stack Senior apasionado por la tecnología para unirse a\nnuestro equipo de desarrollo. Trabajarás en proyectos desafiantes que impactan a\nmillones de usuarios, colaborando con equipos multidisciplinarios en un ambiente\ndinámico y de aprendizaje continuo.\nRESPONSABILIDADES\n•\nDiseñar, desarrollar y mantener aplicaciones web escalables\n•\nParticipar en la arquitectura de soluciones tecnológicas\n•\nColaborar con equipos de diseño, producto y QA\n•\nRealizar revisiones de código y mentorías a desarrolladores junior\n•\nImplementar mejores prácticas de desarrollo y seguridad\n•\nParticipar en ceremonias ágiles (Scrum/Kanban)\nREQUISITOS\nObligatorios:\n•\nTítulo profesional en Ingeniería de Sistemas, Software o afines\n•\nMínimo 4 años de experiencia en desarrollo Full Stack\n•\nDominio de JavaScript/TypeScript, React y Node.js\n•\nExperiencia con bases de datos SQL y NoSQL\n•\nConocimiento en Git y metodologías ágiles\n•\nInglés intermedio (B1 mínimo)\nDeseables:\n•\nExperiencia con AWS, Azure o Google Cloud\n•\nConocimiento en Docker y Kubernetes\n•\nFamiliaridad con arquitecturas de microservicios\n•\nCertificaciones técnicas relevantes\nOFRECEMOS\n•\nSalario competitivo según experiencia: $8.000.000 - $12.000.000 COP\n•\nBonos por desempeño\n•\nTrabajo híbrido (3 días oficina, 2 días remoto)\n•\nSeguro de salud complementario\n•\n15 días hábiles de vacaciones adicionales\n•\nPresupuesto anual para capacitación y certificaciones\n•\nHorario flexible\n•\nDías de cumpleaños libres\n•\nAmbiente de trabajo colaborativo e innovador\nPROCESO DE SELECCIÓN\n1.\nRevisión de hoja de vida\n2.\nPrueba técnica online\n3.\nEntrevista técnica con el equipo\n4.\nEntrevista con RRHH y gerencia\n5.\nVerificación de referencias\nCÓMO APLICAR\nEnvía tu hoja de vida actualizada a: reclutamiento@technovate.com.co\nAsunto: \"Desarrollador Full Stack Senior - [Tu Nombre]\"\nFecha límite para aplicar: 20 de diciembre de 2025\nTechNovate Solutions es un empleador que ofrece igualdad de oportunidades. Valoramos\nla diversidad y estamos comprometidos con crear un ambiente inclusivo para todos\nnuestros empleados.\nContacto:\nwww.technovate.com.co\nTel: +57 (1) 234-5678\nBogotá, Colombia\n",
  "document_metadata": {
    "pages": 2,
    "tables_count": 0,
    "executive_summary": "TechNovate Solutions S.A.S. busca un Desarrollador Full Stack Senior para su equipo en Bogotá en modalidad híbrida (3 días en oficina, 2 días remoto). El rol implica liderar el desarrollo de aplicaciones web escalables dentro de una empresa enfocada en soluciones tecnológicas, participando en el diseño de arquitectura y colaborando con equipos multidisciplinarios en un ambiente innovador.\n\nLas responsabilidades incluyen diseñar, desarrollar y mantener aplicaciones web, participar en la arquitectura de soluciones, colaborar con diseño, producto y QA, realizar revisiones de código y mentoría a desarrolladores junior, implementar buenas prácticas de desarrollo y seguridad, y participar en ceremonias ágiles (Scrum/Kanban).\n\nLos requisitos críticos son al menos 4 años de experiencia, título profesional en Ingeniería de Sistemas, Software o afines, dominio de JavaScript/TypeScript, React y Node.js, manejo de bases de datos SQL y NoSQL, uso de Git y experiencia con metodologías ágiles. Se solicita inglés intermedio (B1) y experiencia en arquitectura y prácticas de seguridad. La experiencia con AWS/Azure/GCP, Docker, Kubernetes y microservicios es deseable pero no excluyente.\n\nAspectos destacables son el rango salarial de $8.000.000–$12.000.000 COP, beneficios como bonos por desempeño, seguro complementario, 15 días hábiles de vacaciones adicionales, presupuesto para capacitación y horario flexible."
  },
  "analysis": {
    "job_id": null,
    "title": "Desarrollador Full Stack Senior",
    "company": "TechNovate Solutions S.A.S.",
    "seniority_level": "Senior",
    "responsibilities": [
      "Diseñar, desarrollar y mantener aplicaciones web escalables",
      "Participar en la arquitectura de soluciones tecnológicas",
      "Colaborar con equipos de diseño, producto y QA",
      "Realizar revisiones de código y mentorías a desarrolladores junior",
      "Implementar mejores prácticas de desarrollo y seguridad",
      "Participar en ceremonias ágiles (Scrum/Kanban)"
    ],
    "technical_requirements": [
      "JavaScript",
      "JS",
      "TypeScript",
      "React",
      "Node.js",
      "Bases de datos SQL",
      "Bases de datos NoSQL",
      "Git",
      "Metodologías ágiles (Scrum/Kanban)",
      "Arquitectura de soluciones",
      "Implementación de mejores prácticas de desarrollo y seguridad"
    ],
    "experience_required": "4 años",
    "education": "Título profesional en Ingeniería de Sistemas, Software o afines",
    "soft_skills": [
      "Trabajo en equipo",
      "Comunicación",
      "Mentoría y revisión de código",
      "Adaptabilidad y aprendizaje continuo",
      "Colaboración multidisciplinaria"
    ],
    "ats_keywords": [
      "Desarrollador Full Stack",
      "Full Stack",
      "JavaScript",
      "JS",
      "TypeScript",
      "React",
      "Node.js",
      "Node",
      "SQL",
      "NoSQL",
      "Git",
      "Scrum",
      "Kanban",
      "Microservicios",
      "Docker",
      "Kubernetes",
      "AWS",
      "Azure",
      "Google Cloud",
      "Arquitectura de soluciones",
      "Revisión de código",
      "Mentoría",
      "Seguridad",
      "Aplicaciones web escalables",
      "Inglés B1",
      "Certificaciones técnicas"
    ],
    "location": "Bogotá, Colombia",
    "work_mode": "Hybrid",
    "salary_range": "$8.000.000 - $12.000.000 COP",
    "benefits": [
      "Bonos por desempeño",
      "Trabajo híbrido (3 días oficina, 2 días remoto)",
      "Seguro de salud complementario",
      "15 días hábiles de vacaciones adicionales",
      "Presupuesto anual para capacitación y certificaciones",
      "Horario flexible",
      "Días de cumpleaños libres",
      "Ambiente de trabajo colaborativo e innovador"
    ],
    "required_languages": [
      "Inglés (Intermedio - B1)"
    ],
    "nice_to_have": [
      "Experiencia con AWS, Azure o Google Cloud",
      "Conocimiento en Docker",
      "Conocimiento en Kubernetes",
      "Familiaridad con arquitecturas de microservicios",
      "Certificaciones técnicas relevantes"
    ],
    "analyzed_at": "2025-12-04T01:46:02.366762"
  },
  "status": "analyzed",
  "created_at": "2025-12-04T01:46:02.367545",
  "updated_at": "2025-12-04T01:46:02.367549"
}